pysensors/__init__.py
pysensors/version.py
pysensors/basis/__init__.py
pysensors/basis/_base.py
pysensors/basis/_custom.py
pysensors/basis/_identity.py
pysensors/basis/_random_projection.py
pysensors/basis/_svd.py
pysensors/classification/__init__.py
pysensors/classification/_sspoc.py
pysensors/optimizers/__init__.py
pysensors/optimizers/_ccqr.py
pysensors/optimizers/_gqr.py
pysensors/optimizers/_qr.py
pysensors/optimizers/_tpgr.py
pysensors/reconstruction/__init__.py
pysensors/reconstruction/_sspor.py
pysensors/utils/__init__.py
pysensors/utils/_base.py
pysensors/utils/_constraints.py
pysensors/utils/_norm_calc.py
pysensors/utils/_optimizers.py
pysensors/utils/_validation.py
python_sensors-0.4.1.dist-info/LICENSE
python_sensors-0.4.1.dist-info/METADATA
python_sensors-0.4.1.dist-info/WHEEL
python_sensors-0.4.1.dist-info/top_level.txt
python_sensors-0.4.1.dist-info/RECORD
