Metadata-Version: 2.1
Name: python-sensors
Version: 0.4.1
Summary: Sparse sensor placement
Home-page: https://github.com/dynamicslab/pysensors
Author: Brian de Silva, Krithika Manohar, Emily Clark
Author-email: bdesilva@uw.edu, kmanohar@uw.edu, emily.e.clark93@gmail.com
License: MIT
Classifier: Programming Language :: Python
Classifier: Programming Language :: Python :: 3.9
Classifier: Programming Language :: Python :: 3.10
Classifier: Programming Language :: Python :: 3.11
Classifier: Programming Language :: Python :: 3.12
Classifier: Development Status :: 4 - Beta
Classifier: Intended Audience :: Science/Research
Classifier: License :: OSI Approved :: MIT License
Classifier: Topic :: Scientific/Engineering :: Mathematics
Requires-Python: >=3.6
License-File: LICENSE
Requires-Dist: scikit-learn>=0.23
Requires-Dist: matplotlib
Requires-Dist: numpy
Requires-Dist: pandas
Requires-Dist: scipy
